distopf/__init__.py
distopf/distOPF.py
distopf/importer.py
distopf/plot.py
distopf/utils.py
distopf/cases/__init__.py
distopf/cases/cim/IEEE123_PV.xml
distopf/cases/cim/IEEE13.xml
distopf/cases/csv/2Bus-1ph-batt/battery_data.csv
distopf/cases/csv/2Bus-1ph-batt/branch_data.csv
distopf/cases/csv/2Bus-1ph-batt/bus_data.csv
distopf/cases/csv/2Bus-1ph-batt/cap_data.csv
distopf/cases/csv/2Bus-1ph-batt/default_loadshape.csv
distopf/cases/csv/2Bus-1ph-batt/gen_data.csv
distopf/cases/csv/2Bus-1ph-batt/pv_loadshape.csv
distopf/cases/csv/2Bus-1ph-batt/reg_data.csv
distopf/cases/csv/3Bus-1ph-batt/battery_data.csv
distopf/cases/csv/3Bus-1ph-batt/branch_data.csv
distopf/cases/csv/3Bus-1ph-batt/bus_data.csv
distopf/cases/csv/3Bus-1ph-batt/cap_data.csv
distopf/cases/csv/3Bus-1ph-batt/default_loadshape.csv
distopf/cases/csv/3Bus-1ph-batt/gen_data.csv
distopf/cases/csv/3Bus-1ph-batt/pv_loadshape.csv
distopf/cases/csv/3Bus-1ph-batt/reg_data.csv
distopf/cases/csv/4Bus-YY-Bal_dss/branch_data.csv
distopf/cases/csv/4Bus-YY-Bal_dss/bus_data.csv
distopf/cases/csv/4Bus-YY-Bal_dss/cap_data.csv
distopf/cases/csv/4Bus-YY-Bal_dss/gen_data.csv
distopf/cases/csv/4Bus-YY-Bal_dss/reg_data.csv
distopf/cases/csv/4Bus-YY-Bal_dss_batt/battery_data.csv
distopf/cases/csv/4Bus-YY-Bal_dss_batt/branch_data.csv
distopf/cases/csv/4Bus-YY-Bal_dss_batt/bus_data.csv
distopf/cases/csv/4Bus-YY-Bal_dss_batt/cap_data.csv
distopf/cases/csv/4Bus-YY-Bal_dss_batt/default_loadshape.csv
distopf/cases/csv/4Bus-YY-Bal_dss_batt/gen_data.csv
distopf/cases/csv/4Bus-YY-Bal_dss_batt/pv_loadshape.csv
distopf/cases/csv/4Bus-YY-Bal_dss_batt/reg_data.csv
distopf/cases/csv/9500/branch_data.csv
distopf/cases/csv/9500/bus_data.csv
distopf/cases/csv/9500/cap_data.csv
distopf/cases/csv/9500/gen_data.csv
distopf/cases/csv/9500/reg_data.csv
distopf/cases/csv/9500-primary-network/branch_data.csv
distopf/cases/csv/9500-primary-network/bus_data.csv
distopf/cases/csv/9500-primary-network/cap_data.csv
distopf-0.3.1.dist-info/METADATA
distopf-0.3.1.dist-info/WHEEL
distopf-0.3.1.dist-info/licenses/LICENSE.md
distopf-0.3.1.dist-info/RECORD
