Metadata-Version: 2.4
Name: distopf
Version: 0.3.1
Summary: A package for solving unbalanced three-phase distribution system optimal power flow problems.
Project-URL: Homepage, https://github.com/GRIDAPPSD/distopf
Project-URL: Issues, https://github.com/GRIDAPPSD/distopf/issues
Author: Abodh Poudyal
Author-email: Nathan Gray <nathan.gray@pnnl.gov>, Rabayet Sadnan <rabayet.sadnan@pnnl.gov>
License-File: LICENSE.md
Requires-Python: >=3.10
Requires-Dist: cim-graph==0.4.1a2
Requires-Dist: cvxpy>=1.7.2
Requires-Dist: gridappsd-python<2026.0.0,>=2025.3.2a1
Requires-Dist: networkx>=3.4.2
Requires-Dist: numpy>=2.2.6
Requires-Dist: opendssdirect-py==0.8.4
Requires-Dist: pandas>=2.3.3
Requires-Dist: plotly>=6.3.0
Requires-Dist: pyomo>=6.9.4
Requires-Dist: scipy>=1.15.3
